vresutils/__init__.py
vresutils/array.py
vresutils/benchmark.py
vresutils/costdata.py
vresutils/costdata2.py
vresutils/decorators.py
vresutils/dispatch.py
vresutils/entsoe.py
vresutils/file_io_helper.py
vresutils/flow.py
vresutils/flowtracing.py
vresutils/graph.py
vresutils/grid.py
vresutils/gurobi.py
vresutils/hydro.py
vresutils/landuse.py
vresutils/load.py
vresutils/mapping.py
vresutils/plot.py
vresutils/reatlas.py
vresutils/shapes.py
vresutils/snakemake.py
vresutils/transfer.py
vresutils-0.3.1.dist-info/LICENSE.txt
vresutils-0.3.1.dist-info/METADATA
vresutils-0.3.1.dist-info/WHEEL
vresutils-0.3.1.dist-info/top_level.txt
vresutils-0.3.1.dist-info/RECORD
