Metadata-Version: 2.1
Name: vresutils
Version: 0.3.1
Summary: Varying Renewable Energy System Utilities
Home-page: https://github.com/FRESNA/vresutils
Author: Jonas Hoersch (KIT,FIAS), David Schlachtberger (FIAS), Sarah Becker (FIAS)
Author-email: jonas.hoersch@posteo.de
License: GPLv3
Platform: UNKNOWN
Classifier: Development Status :: 3 - Alpha
Classifier: Environment :: Console
Classifier: Intended Audience :: Science/Research
Classifier: License :: OSI Approved :: GNU General Public License v3 or later (GPLv3+)
Classifier: Natural Language :: English
Classifier: Operating System :: OS Independent
Requires-Dist: countrycode
Requires-Dist: fiona
Requires-Dist: matplotlib
Requires-Dist: memory-profiler
Requires-Dist: networkx (>=2)
Requires-Dist: numpy
Requires-Dist: pandas (>=0.19.0)
Requires-Dist: pyomo
Requires-Dist: pyproj
Requires-Dist: pyshp
Requires-Dist: rasterio (>=1.0)
Requires-Dist: scipy
Requires-Dist: shapely
Requires-Dist: six
